disterminal/__init__.py
disterminal/cli.py
disterminal/helpers.py
disterminal/messages.py
disterminal/plotting.py
disterminal/terminalsize.py
disterminal-0.2.1.dist-info/METADATA
disterminal-0.2.1.dist-info/RECORD
disterminal-0.2.1.dist-info/WHEEL
disterminal-0.2.1.dist-info/entry_points.txt
disterminal-0.2.1.dist-info/top_level.txt
