Metadata-Version: 2.1
Name: disterminal
Version: 0.2.1
Summary: distribution plotting in your terminal
Home-page: https://github.com/jlmcgehee21/disterminal
Author: Jeff McGehee
Author-email: jlmcgehee21@gmail.com
License: MIT license
Keywords: disterminal
Platform: UNKNOWN
Classifier: Development Status :: 2 - Pre-Alpha
Classifier: Intended Audience :: Developers
Classifier: License :: OSI Approved :: MIT License
Classifier: Natural Language :: English
Classifier: Programming Language :: Python :: 2
Classifier: Programming Language :: Python :: 2.7
Classifier: Programming Language :: Python :: 3
Classifier: Programming Language :: Python :: 3.4
Classifier: Programming Language :: Python :: 3.5
Classifier: Programming Language :: Python :: 3.6
Requires-Dist: Click (>=6.0)
Requires-Dist: scipy (==1.0.0)
Requires-Dist: fabulous (==0.3.0)
